missingno/__init__.py
missingno/_version.py
missingno/missingno.py
missingno/utils.py
missingno-0.5.2.dist-info/LICENSE.md
missingno-0.5.2.dist-info/METADATA
missingno-0.5.2.dist-info/WHEEL
missingno-0.5.2.dist-info/top_level.txt
missingno-0.5.2.dist-info/RECORD
